Metadata-Version: 2.4
Name: fustor_pusher_fusion
Version: 0.2.16
Summary: Fustor agent pusher driver for the Fustor Fusion service.
Author-email: Huajin Wang <wanghuajin999@163.com>
License-Expression: MIT
Project-URL: Homepage, https://github.com/excelwang/fustor/tree/master/packages/pusher_fusion
Project-URL: Bug Tracker, https://github.com/excelwang/fustor/issues
Classifier: Programming Language :: Python :: 3
Classifier: Operating System :: OS Independent
Requires-Python: >=3.11
Requires-Dist: fustor-core
Requires-Dist: fustor-fusion-sdk
